{
  "hash": "-7de3b7b6",
  "content": "Hacker News Hacker News new | past | comments | ask | show | jobs | submit login 1. Filing the corners off my MacBooks ( kentwalters.com ) 741 points by normanvalentine 10 hours ago | hide | 373&nbsp;comments 2. Starfling: A one-tap endless orbital slingshot game in a single HTML file ( playstarfling.com ) 128 points by iceberger2001 5 hours ago | hide | 37&nbsp;comments 3. 1D Chess ( rowan441.github.io ) 793 points by burnt-resistor 16 hours ago | hide | 142&nbsp;comments 4. Artemis II safely splashes down ( cbsnews.com ) 842 points by areoform 8 hours ago | hide | 268&nbsp;comments 5. Installing every* Firefox extension ( jack.cab ) 362 points by RohanAdwankar 10 hours ago | hide | 43&nbsp;comments 6. Chimpanzees in Uganda locked in eight-year &#x27;civil war&#x27;, say researchers ( bbc.com ) 323 points by neversaydie 13 hours ago | hide | 180&nbsp;comments 7. Volunteers turn a fan&#x27;s recordings of 10K concerts into an online treasure trove ( apnews.com ) 32 points by geox 3 hours ago | hide | 1&nbsp;comment 8. 20 years on AWS and never not my job ( daemonology.net ) 126 points by cperciva 3 hours ago | hide | 16&nbsp;comments 9. Great at gaming? US air traffic control wants you to apply ( bbc.com ) 27 points by 1659447091 3 hours ago | hide | 34&nbsp;comments 10. WireGuard makes new Windows release following Microsoft signing resolution ( zx2c4.com ) 462 points by zx2c4 16 hours ago | hide | 133&nbsp;comments 11. AI assistance when contributing to the Linux kernel ( github.com/torvalds ) 301 points by hmokiguess 14 hours ago | hide | 197&nbsp;comments 12. Industrial design files for Keychron keyboards and mice ( github.com/keychron ) 368 points by stingraycharles 16 hours ago | hide | 111&nbsp;comments 13. Bevy game development tutorials and in-depth resources ( taintedcoders.com ) 77 points by GenericCanadian 7 hours ago | hide | 14&nbsp;comments 14. Flashback to a time when government reports were works of art ( chicagotribune.com ) 17 points by NaOH 3 hours ago | hide | 4&nbsp;comments 15. A practical guide for setting up Zettelkasten method in Obsidian ( desktopcommander.app ) 47 points by rkrizanovskis 6 hours ago | hide | 20&nbsp;comments 16. JSON formatter Chrome plugin now closed and injecting adware ( github.com/callumlocke ) 212 points by jkl5xx 14 hours ago | hide | 109&nbsp;comments 17. CPU-Z and HWMonitor compromised ( theregister.com ) 319 points by pashadee 19 hours ago | hide | 89&nbsp;comments 18. Quien – A better WHOIS lookup tool ( github.com/retlehs ) 38 points by bretthopper 5 hours ago | hide | 10&nbsp;comments 19. Helium is hard to replace ( construction-physics.com ) 305 points by JumpCrisscross 17 hours ago | hide | 210&nbsp;comments 20. Productive Procrastination ( maxvanijsselmuiden.nl ) 14 points by maxvij 3 hours ago | hide | 6&nbsp;comments 21. Optimal Strategy for Connect 4 ( 2swap.github.io ) 4 points by marvinborner 1 hour ago | hide | 1&nbsp;comment 22. The Seasons Are Wrong ( kentwalters.com ) 16 points by NikxDa 4 hours ago | hide | 20&nbsp;comments 23. The Bra-and-Girdle Maker That Fashioned the Impossible for NASA ( mitpress.mit.edu ) 85 points by sohkamyung 10 hours ago | hide | 4&nbsp;comments 24. Italo Calvino: A traveller in a world of uncertainty ( historytoday.com ) 70 points by lermontov 8 hours ago | hide | 13&nbsp;comments 25. Investigating Split Locks on x86-64 ( chipsandcheese.com ) 54 points by ingve 8 hours ago | hide | 16&nbsp;comments 26. Moooooonitoring the Cow.txt Herd ( moooo.farm ) 4 points by pabs3 1 hour ago | hide | discuss 27. Watgo – A WebAssembly Toolkit for Go ( thegreenplace.net ) 93 points by ibobev 13 hours ago | hide | 7&nbsp;comments 28. What is RISC-V and why it matters to Canonical ( ubuntu.com ) 126 points by fork-bomber 14 hours ago | hide | 87&nbsp;comments 29. Launch HN: Twill.ai (YC S25) – Delegate to cloud agents, get back PRs ( twill.ai ) 67 points by danoandco 13 hours ago | hide | 63&nbsp;comments 30. A compelling title that is cryptic enough to get you to take action on it ( ericwbailey.website ) 220 points by mooreds 15 hours ago | hide | 119&nbsp;comments More Guidelines | FAQ | Lists | API | Security | Legal | Apply to YC | Contact Search:",
  "statusCode": 200,
  "checkedAt": "2026-04-11T08:38:22.810Z",
  "site": "Hacker News",
  "category": "Tech News"
}